{"save_date":"2020-09-26T02:42:19.714Z","file_version":3,"items":[{"category":{"save_id":"id20200908074629","name":"Rust","created_at":"2020-09-07T22:46:29.201Z","id":30},"show_id":"20200908074854","title":"New release , サイト追加","content":"Rust WebAssembly 関連記事のサイト、追加しました","created_at":"2020-09-07T22:48:54.458Z","id":74},{"category":{"save_id":"id20200908074629","name":"Rust","created_at":"2020-09-07T22:46:29.201Z","id":30},"show_id":"20200908075018","title":"Rust WebAssembly 関連公開しております。","content":"note で、Rust WebAssembly 関連記事を公開しています。\n\n***\nhttps://note.com/knaka0209/m/m0c9d56391170\n","created_at":"2020-09-07T22:50:18.329Z","id":75},{"category":{"save_id":"id20200908074629","name":"Rust","created_at":"2020-09-07T22:46:29.201Z","id":30},"show_id":"20200908080733","title":"CMS関連ページを、追加しました","content":"***\n* 下記ＵＲＬとなります。\n\nhttps://kuc-arc-f.github.io/cms-wasm-dev/#/pages/id20200908075238","created_at":"2020-09-07T23:07:33.840Z","id":76},{"category":{"save_id":"id20200908074629","name":"Rust","created_at":"2020-09-07T22:46:29.201Z","id":30},"show_id":"20200910070659","title":"React IndexedDB CRUD 事例を追加しました。","content":"React IndexedDB CRUD 事例を追加しました。\n\n***\n\n* 下記URLとなります。\n\nhttps://kuc-arc-f.github.io/wasm-idx-sample/#/task\n\n","created_at":"2020-09-09T22:06:59.991Z","id":77},{"category":{"save_id":"id20200908074629","name":"Rust","created_at":"2020-09-07T22:46:29.201Z","id":32},"show_id":"20200911181616","title":"Rust json (serde_json) デコード等の説明を、追加しました。","content":"\n***\n\n* Rust serde_json で、serialized　、デコード(deserialized) ,vect適用する例\n\nhttps://gist.github.com/kuc-arc-f/f108b6253ca30baf57ff9a2767517888\n\n***\n* Rust serde_json ,jsonから、　配列変換(array * object)で、繰り返し処理の例\n\nhttps://gist.github.com/kuc-arc-f/ed58efa32591815786661b32d6501d75\n","created_at":"2020-09-11T09:16:16.005Z","id":78},{"category":{"save_id":"id20200908074629","name":"Rust","created_at":"2020-09-07T22:46:29.201Z","id":34},"show_id":"20200915113351","title":"javascript , wasm の画面描画の速度比較の結果を追記しました。","content":"\n***\n* 下記URLとなります。\n\nhttps://github.com/kuc-arc-f/wasm-idx-2test/blob/master/README.md\n\n","created_at":"2020-09-15T02:33:51.393Z","id":79},{"category":{"save_id":"id20200908074629","name":"Rust","created_at":"2020-09-07T22:46:29.201Z","id":36},"show_id":"20200916170222","title":"wasmの、文字検索の処理を追加しました。","content":"***\n・下記ＵＲＬです。\n\nhttps://github.com/kuc-arc-f/wasm-idx-3search","created_at":"2020-09-16T08:02:22.368Z","id":80}],"category_items":[{"save_id":"id20200908074629","name":"Rust","created_at":"2020-09-07T22:46:29.201Z","id":40},{"save_id":"id20200908074636","name":"その他","created_at":"2020-09-07T22:46:36.033Z","id":41}],"page_items":[{"save_id":"id20200908074643","title":"About","content":"\n***\n* 開発者向けの、Rust WebAssembly 　事例、ノウハウに関する記事を掲載予定です\n\n* オープンソースで、公開を予定しております\n","created_at":"2020-09-07T22:46:43.674Z","id":33},{"save_id":"id20200908075238","title":"Wasm CMS作成","content":"Rust WebAssembly で作成した。CMSデモ URLを公開しています、\n\n***\n### webpack版\n\n* 初版\n\nhttps://kuc-arc-f.github.io/cms-wasm-sample-type1/\n\n* type5, TOP画像なし, グレー\n\nhttps://kuc-arc-f.github.io/cms-wasm-sample-type5/\n\n***\n### CDN 版\n\n* type5, TOP画像なし, グレー\n\nhttps://wasm-cms-type5-kuc.netlify.app/\n\n","created_at":"2020-09-07T22:52:38.146Z","id":34},{"save_id":"id20200910070520","title":"製作事例","content":"wasm + React 製作事例を追加しました。\n\n***\n\n### wasm CRUD, React IndexedDB 事例\n\n* デモURLとなります。\n\nhttps://kuc-arc-f.github.io/wasm-idx-sample/\n\n* コードURL\n\nhttps://github.com/kuc-arc-f/wasm-idx-1crud\n\n***\n### Sqlite3 + Rust サンプル\n\nhttps://github.com/kuc-arc-f/rust-sqlite-test\n\n***\n### node/express + wasm で、node側でHTML レンダリングする例を追加しました。\n\n* code URL\n\nhttps://github.com/kuc-arc-f/app7_9wasm\n\n***\n","created_at":"2020-09-09T22:05:20.813Z","id":35}]}